README
setup.py
ether/__init__.py
ether/abis.py
ether/chains.py
ether/client.py
ether/utils.py
ether/wallet.py
ether/ws.py
ether/dex/__init__.py
ether/dex/balancer.py
ether/dex/curve.py
ether/dex/curve_router.py
ether/dex/limit_order.py
ether/dex/swap.py
ether/dex/univ2.py
ether/dex/univ3.py
ether/flashbots/__init__.py
ether/flashbots/blox.py
ether/flashbots/flashbots.py
ether/flashbots/middleware.py
ether/flashbots/provider.py
ether/flashbots/types.py
ether/middlewares/__init__.py
ether/middlewares/argus.py
ether/middlewares/mpc.py
ether/middlewares/remote_signer.py
ether/tools/__init__.py
ether/tools/erc20_balance.py
ether/tools/mnemonic.py
liechains.egg-info/PKG-INFO
liechains.egg-info/SOURCES.txt
liechains.egg-info/dependency_links.txt
liechains.egg-info/requires.txt
liechains.egg-info/top_level.txt