Metadata-Version: 2.2
Name: liechains
Version: 0.4.8
Summary: toolkit for blockchains
Author: leeliewhite
Author-email: leeliewhite@gmail.com
Classifier: Programming Language :: Python :: 3
Classifier: License :: OSI Approved :: MIT License
Classifier: Operating System :: OS Independent
Requires-Python: >=3.9
Requires-Dist: web3<=6.15.1
Requires-Dist: websocket-client
Requires-Dist: cryptography
Requires-Dist: cobo_waas2
Dynamic: author
Dynamic: author-email
Dynamic: classifier
Dynamic: requires-dist
Dynamic: requires-python
Dynamic: summary
